dbyml/__init__.py
dbyml/base.py
dbyml/buildx.py
dbyml/config.py
dbyml/errors.py
dbyml/image.py
dbyml/prompt.py
dbyml/registry.py
dbyml/data/full.yml
dbyml/data/old.yml
dbyml/data/templates/buildkitd.toml.j2
dbyml-1.4.0.dist-info/LICENSE
dbyml-1.4.0.dist-info/METADATA
dbyml-1.4.0.dist-info/WHEEL
dbyml-1.4.0.dist-info/entry_points.txt
dbyml-1.4.0.dist-info/top_level.txt
dbyml-1.4.0.dist-info/RECORD
