Metadata-Version: 2.1
Name: dbyml
Version: 1.4.0
Summary: "CLI tool for building docker image"
Home-page: UNKNOWN
Author: git-ogawa
Author-email: stu1232541964@gmail.com
License: UNKNOWN
Keywords: docker,python
Platform: UNKNOWN
Classifier: Operating System :: POSIX :: Linux
Classifier: Programming Language :: Python :: 3
Classifier: Programming Language :: Python :: 3 :: Only
Classifier: Programming Language :: Python :: 3.8
Classifier: Programming Language :: Python :: 3.9
Classifier: Programming Language :: Python :: 3.10
Classifier: Programming Language :: Python :: 3.11
Requires-Python: >=3.8
Requires-Dist: docker (>=5.0.0)
Requires-Dist: jinja2 (>=2.11.3)
Requires-Dist: prompt-toolkit (>=3.0.29)
Requires-Dist: requests (>=2.27.1)
Requires-Dist: ruamel.yaml (>=0.17.16)
Requires-Dist: wheel (>=0.36.0)
Provides-Extra: dev
Requires-Dist: black ; extra == 'dev'
Requires-Dist: flake8 ; extra == 'dev'
Requires-Dist: mypy ; extra == 'dev'
Requires-Dist: pytest ; extra == 'dev'
Requires-Dist: pytest-cov ; extra == 'dev'
Requires-Dist: pytest-docker ; extra == 'dev'
Requires-Dist: pytest-html ; extra == 'dev'
Requires-Dist: pytest-mock ; extra == 'dev'
Requires-Dist: tox ; extra == 'dev'
Requires-Dist: types-requests ; extra == 'dev'
Requires-Dist: yamllint ; extra == 'dev'
